[
  {
    "ticker": "NVDA",
    "rank": 1,
    "currentPrice": 0.0,
    "predictedPrice": 0.0,
    "expectedReturnPct": null,
    "confidence": 0.64,
    "score": 50.0,
    "rankingScore": 0.48639,
    "horizon": "1y",
    "sector": null,
    "marketCap": 5027184000000,
    "marketCapBucket": "mega",
    "volume": null,
    "ma50": 182.497,
    "ma200": 148.581,
    "trend": "bullish",
    "volatility_10d": null,
    "sentiment_score": null,
    "buzz": null,
    "pe_ratio": null,
    "peg_ratio": null,
    "dividend_yield": null,
    "timestamp": "2025-11-03T23:37:31.132444",
    "reason": "heuristic fallback",
    "explain_factors": {
      "expectedReturnPct_norm": 0.0,
      "confidence_weight": 0.5354,
      "model_quality_norm": 0.4621,
      "technical": 0.8,
      "sentiment_factor": 1.0,
      "fundamentals": 1.0,
      "health_factor": 1.0
    }
  },
  {
    "ticker": "AAPL",
    "rank": 2,
    "currentPrice": 0.0,
    "predictedPrice": 0.0,
    "expectedReturnPct": null,
    "confidence": 0.64,
    "score": 50.0,
    "rankingScore": 0.48639,
    "horizon": "1y",
    "sector": null,
    "marketCap": 3975577774650,
    "marketCapBucket": "mega",
    "volume": null,
    "ma50": 249.074,
    "ma200": 223.506,
    "trend": "bullish",
    "volatility_10d": null,
    "sentiment_score": null,
    "buzz": null,
    "pe_ratio": null,
    "peg_ratio": null,
    "dividend_yield": null,
    "timestamp": "2025-11-03T23:37:31.140349",
    "reason": "heuristic fallback",
    "explain_factors": {
      "expectedReturnPct_norm": 0.0,
      "confidence_weight": 0.5354,
      "model_quality_norm": 0.4621,
      "technical": 0.8,
      "sentiment_factor": 1.0,
      "fundamentals": 1.0,
      "health_factor": 1.0
    }
  },
  {
    "ticker": "MSFT",
    "rank": 3,
    "currentPrice": 0.0,
    "predictedPrice": 0.0,
    "expectedReturnPct": null,
    "confidence": 0.64,
    "score": 50.0,
    "rankingScore": 0.48639,
    "horizon": "1y",
    "sector": null,
    "marketCap": 3842762218965,
    "marketCapBucket": "mega",
    "volume": null,
    "ma50": 514.021,
    "ma200": 461.604,
    "trend": "bullish",
    "volatility_10d": null,
    "sentiment_score": null,
    "buzz": null,
    "pe_ratio": null,
    "peg_ratio": null,
    "dividend_yield": null,
    "timestamp": "2025-11-03T23:37:31.140349",
    "reason": "heuristic fallback",
    "explain_factors": {
      "expectedReturnPct_norm": 0.0,
      "confidence_weight": 0.5354,
      "model_quality_norm": 0.4621,
      "technical": 0.8,
      "sentiment_factor": 1.0,
      "fundamentals": 1.0,
      "health_factor": 1.0
    }
  },
  {
    "ticker": "GOOG",
    "rank": 4,
    "currentPrice": 0.0,
    "predictedPrice": 0.0,
    "expectedReturnPct": null,
    "confidence": 0.64,
    "score": 50.0,
    "rankingScore": 0.48639,
    "horizon": "1y",
    "sector": null,
    "marketCap": 3396526140000,
    "marketCapBucket": "mega",
    "volume": null,
    "ma50": 246.004,
    "ma200": 194.454,
    "trend": "bullish",
    "volatility_10d": null,
    "sentiment_score": null,
    "buzz": null,
    "pe_ratio": null,
    "peg_ratio": null,
    "dividend_yield": null,
    "timestamp": "2025-11-03T23:37:31.140349",
    "reason": "heuristic fallback",
    "explain_factors": {
      "expectedReturnPct_norm": 0.0,
      "confidence_weight": 0.5354,
      "model_quality_norm": 0.4621,
      "technical": 0.8,
      "sentiment_factor": 1.0,
      "fundamentals": 1.0,
      "health_factor": 1.0
    }
  },
  {
    "ticker": "GOOGL",
    "rank": 5,
    "currentPrice": 0.0,
    "predictedPrice": 0.0,
    "expectedReturnPct": null,
    "confidence": 0.64,
    "score": 50.0,
    "rankingScore": 0.48639,
    "horizon": "1y",
    "sector": null,
    "marketCap": 3423649240000,
    "marketCapBucket": "mega",
    "volume": null,
    "ma50": 245.41,
    "ma200": 193.184,
    "trend": "bullish",
    "volatility_10d": null,
    "sentiment_score": null,
    "buzz": null,
    "pe_ratio": null,
    "peg_ratio": null,
    "dividend_yield": null,
    "timestamp": "2025-11-03T23:37:31.155130",
    "reason": "heuristic fallback",
    "explain_factors": {
      "expectedReturnPct_norm": 0.0,
      "confidence_weight": 0.5354,
      "model_quality_norm": 0.4621,
      "technical": 0.8,
      "sentiment_factor": 1.0,
      "fundamentals": 1.0,
      "health_factor": 1.0
    }
  },
  {
    "ticker": "AMZN",
    "rank": 6,
    "currentPrice": 0.0,
    "predictedPrice": 0.0,
    "expectedReturnPct": null,
    "confidence": 0.64,
    "score": 50.0,
    "rankingScore": 0.48639,
    "horizon": "1y",
    "sector": null,
    "marketCap": 2715314866794,
    "marketCapBucket": "mega",
    "volume": null,
    "ma50": 225.994,
    "ma200": 214.619,
    "trend": "bullish",
    "volatility_10d": null,
    "sentiment_score": null,
    "buzz": null,
    "pe_ratio": null,
    "peg_ratio": null,
    "dividend_yield": null,
    "timestamp": "2025-11-03T23:37:31.155130",
    "reason": "heuristic fallback",
    "explain_factors": {
      "expectedReturnPct_norm": 0.0,
      "confidence_weight": 0.5354,
      "model_quality_norm": 0.4621,
      "technical": 0.8,
      "sentiment_factor": 1.0,
      "fundamentals": 1.0,
      "health_factor": 1.0
    }
  },
  {
    "ticker": "META",
    "rank": 7,
    "currentPrice": 0.0,
    "predictedPrice": 0.0,
    "expectedReturnPct": null,
    "confidence": 0.64,
    "score": 50.0,
    "rankingScore": 0.48639,
    "horizon": "1y",
    "sector": null,
    "marketCap": 1607365653883,
    "marketCapBucket": "mega",
    "volume": null,
    "ma50": 736.258,
    "ma200": 678.674,
    "trend": "bullish",
    "volatility_10d": null,
    "sentiment_score": null,
    "buzz": null,
    "pe_ratio": null,
    "peg_ratio": null,
    "dividend_yield": null,
    "timestamp": "2025-11-03T23:37:31.163157",
    "reason": "heuristic fallback",
    "explain_factors": {
      "expectedReturnPct_norm": 0.0,
      "confidence_weight": 0.5354,
      "model_quality_norm": 0.4621,
      "technical": 0.8,
      "sentiment_factor": 1.0,
      "fundamentals": 1.0,
      "health_factor": 1.0
    }
  },
  {
    "ticker": "AVGO",
    "rank": 8,
    "currentPrice": 0.0,
    "predictedPrice": 0.0,
    "expectedReturnPct": null,
    "confidence": 0.64,
    "score": 50.0,
    "rankingScore": 0.48639,
    "horizon": "1y",
    "sector": null,
    "marketCap": 1712093438726,
    "marketCapBucket": "mega",
    "volume": null,
    "ma50": 340.609,
    "ma200": 259.592,
    "trend": "bullish",
    "volatility_10d": null,
    "sentiment_score": null,
    "buzz": null,
    "pe_ratio": null,
    "peg_ratio": null,
    "dividend_yield": null,
    "timestamp": "2025-11-03T23:37:31.163157",
    "reason": "heuristic fallback",
    "explain_factors": {
      "expectedReturnPct_norm": 0.0,
      "confidence_weight": 0.5354,
      "model_quality_norm": 0.4621,
      "technical": 0.8,
      "sentiment_factor": 1.0,
      "fundamentals": 1.0,
      "health_factor": 1.0
    }
  },
  {
    "ticker": "TSLA",
    "rank": 9,
    "currentPrice": 0.0,
    "predictedPrice": 0.0,
    "expectedReturnPct": null,
    "confidence": 0.64,
    "score": 50.0,
    "rankingScore": 0.48639,
    "horizon": "1y",
    "sector": null,
    "marketCap": 1557713923248,
    "marketCapBucket": "mega",
    "volume": null,
    "ma50": 413.207,
    "ma200": 337.324,
    "trend": "bullish",
    "volatility_10d": null,
    "sentiment_score": null,
    "buzz": null,
    "pe_ratio": null,
    "peg_ratio": null,
    "dividend_yield": null,
    "timestamp": "2025-11-03T23:37:31.171570",
    "reason": "heuristic fallback",
    "explain_factors": {
      "expectedReturnPct_norm": 0.0,
      "confidence_weight": 0.5354,
      "model_quality_norm": 0.4621,
      "technical": 0.8,
      "sentiment_factor": 1.0,
      "fundamentals": 1.0,
      "health_factor": 1.0
    }
  },
  {
    "ticker": "TSM",
    "rank": 10,
    "currentPrice": 0.0,
    "predictedPrice": 0.0,
    "expectedReturnPct": null,
    "confidence": 0.64,
    "score": 50.0,
    "rankingScore": 0.48639,
    "horizon": "1y",
    "sector": null,
    "marketCap": 1266560460016.8235,
    "marketCapBucket": "mega",
    "volume": null,
    "ma50": 275.703,
    "ma200": 219.218,
    "trend": "bullish",
    "volatility_10d": null,
    "sentiment_score": null,
    "buzz": null,
    "pe_ratio": null,
    "peg_ratio": null,
    "dividend_yield": null,
    "timestamp": "2025-11-03T23:37:31.171570",
    "reason": "heuristic fallback",
    "explain_factors": {
      "expectedReturnPct_norm": 0.0,
      "confidence_weight": 0.5354,
      "model_quality_norm": 0.4621,
      "technical": 0.8,
      "sentiment_factor": 1.0,
      "fundamentals": 1.0,
      "health_factor": 1.0
    }
  },
  {
    "ticker": "WMT",
    "rank": 11,
    "currentPrice": 0.0,
    "predictedPrice": 0.0,
    "expectedReturnPct": null,
    "confidence": 0.64,
    "score": 50.0,
    "rankingScore": 0.48639,
    "horizon": "1y",
    "sector": null,
    "marketCap": 809961945484,
    "marketCapBucket": "mega",
    "volume": null,
    "ma50": 102.563,
    "ma200": 97.467,
    "trend": "bullish",
    "volatility_10d": null,
    "sentiment_score": null,
    "buzz": null,
    "pe_ratio": null,
    "peg_ratio": null,
    "dividend_yield": null,
    "timestamp": "2025-11-03T23:37:31.187014",
    "reason": "heuristic fallback",
    "explain_factors": {
      "expectedReturnPct_norm": 0.0,
      "confidence_weight": 0.5354,
      "model_quality_norm": 0.4621,
      "technical": 0.8,
      "sentiment_factor": 1.0,
      "fundamentals": 1.0,
      "health_factor": 1.0
    }
  },
  {
    "ticker": "JPM",
    "rank": 12,
    "currentPrice": 0.0,
    "predictedPrice": 0.0,
    "expectedReturnPct": null,
    "confidence": 0.64,
    "score": 50.0,
    "rankingScore": 0.48639,
    "horizon": "1y",
    "sector": null,
    "marketCap": 842112570000,
    "marketCapBucket": "mega",
    "volume": null,
    "ma50": 305.088,
    "ma200": 275.025,
    "trend": "bullish",
    "volatility_10d": null,
    "sentiment_score": null,
    "buzz": null,
    "pe_ratio": null,
    "peg_ratio": null,
    "dividend_yield": null,
    "timestamp": "2025-11-03T23:37:31.192761",
    "reason": "heuristic fallback",
    "explain_factors": {
      "expectedReturnPct_norm": 0.0,
      "confidence_weight": 0.5354,
      "model_quality_norm": 0.4621,
      "technical": 0.8,
      "sentiment_factor": 1.0,
      "fundamentals": 1.0,
      "health_factor": 1.0
    }
  },
  {
    "ticker": "ORCL",
    "rank": 13,
    "currentPrice": 0.0,
    "predictedPrice": 0.0,
    "expectedReturnPct": null,
    "confidence": 0.64,
    "score": 50.0,
    "rankingScore": 0.48639,
    "horizon": "1y",
    "sector": null,
    "marketCap": 735076873199,
    "marketCapBucket": "mega",
    "volume": null,
    "ma50": 278.52,
    "ma200": 206.544,
    "trend": "bullish",
    "volatility_10d": null,
    "sentiment_score": null,
    "buzz": null,
    "pe_ratio": null,
    "peg_ratio": null,
    "dividend_yield": null,
    "timestamp": "2025-11-03T23:37:31.198783",
    "reason": "heuristic fallback",
    "explain_factors": {
      "expectedReturnPct_norm": 0.0,
      "confidence_weight": 0.5354,
      "model_quality_norm": 0.4621,
      "technical": 0.8,
      "sentiment_factor": 1.0,
      "fundamentals": 1.0,
      "health_factor": 1.0
    }
  },
  {
    "ticker": "MA",
    "rank": 14,
    "currentPrice": 0.0,
    "predictedPrice": 0.0,
    "expectedReturnPct": null,
    "confidence": 0.64,
    "score": 50.0,
    "rankingScore": 0.48639,
    "horizon": "1y",
    "sector": null,
    "marketCap": 488572601021,
    "marketCapBucket": "mega",
    "volume": null,
    "ma50": 575.311,
    "ma200": 560.734,
    "trend": "bullish",
    "volatility_10d": null,
    "sentiment_score": null,
    "buzz": null,
    "pe_ratio": null,
    "peg_ratio": null,
    "dividend_yield": null,
    "timestamp": "2025-11-03T23:37:31.215778",
    "reason": "heuristic fallback",
    "explain_factors": {
      "expectedReturnPct_norm": 0.0,
      "confidence_weight": 0.5354,
      "model_quality_norm": 0.4621,
      "technical": 0.8,
      "sentiment_factor": 1.0,
      "fundamentals": 1.0,
      "health_factor": 1.0
    }
  },
  {
    "ticker": "XOM",
    "rank": 15,
    "currentPrice": 0.0,
    "predictedPrice": 0.0,
    "expectedReturnPct": null,
    "confidence": 0.64,
    "score": 50.0,
    "rankingScore": 0.48639,
    "horizon": "1y",
    "sector": null,
    "marketCap": 479725920000,
    "marketCapBucket": "mega",
    "volume": null,
    "ma50": 113.239,
    "ma200": 110.071,
    "trend": "bullish",
    "volatility_10d": null,
    "sentiment_score": null,
    "buzz": null,
    "pe_ratio": null,
    "peg_ratio": null,
    "dividend_yield": null,
    "timestamp": "2025-11-03T23:37:31.220804",
    "reason": "heuristic fallback",
    "explain_factors": {
      "expectedReturnPct_norm": 0.0,
      "confidence_weight": 0.5354,
      "model_quality_norm": 0.4621,
      "technical": 0.8,
      "sentiment_factor": 1.0,
      "fundamentals": 1.0,
      "health_factor": 1.0
    }
  },
  {
    "ticker": "NFLX",
    "rank": 16,
    "currentPrice": 0.0,
    "predictedPrice": 0.0,
    "expectedReturnPct": null,
    "confidence": 0.64,
    "score": 50.0,
    "rankingScore": 0.48639,
    "horizon": "1y",
    "sector": null,
    "marketCap": 466143703310,
    "marketCapBucket": "mega",
    "volume": null,
    "ma50": 1193.474,
    "ma200": 1123.065,
    "trend": "bullish",
    "volatility_10d": null,
    "sentiment_score": null,
    "buzz": null,
    "pe_ratio": null,
    "peg_ratio": null,
    "dividend_yield": null,
    "timestamp": "2025-11-03T23:37:31.223649",
    "reason": "heuristic fallback",
    "explain_factors": {
      "expectedReturnPct_norm": 0.0,
      "confidence_weight": 0.5354,
      "model_quality_norm": 0.4621,
      "technical": 0.8,
      "sentiment_factor": 1.0,
      "fundamentals": 1.0,
      "health_factor": 1.0
    }
  },
  {
    "ticker": "JNJ",
    "rank": 17,
    "currentPrice": 0.0,
    "predictedPrice": 0.0,
    "expectedReturnPct": null,
    "confidence": 0.64,
    "score": 50.0,
    "rankingScore": 0.48639,
    "horizon": "1y",
    "sector": null,
    "marketCap": 448755305699,
    "marketCapBucket": "mega",
    "volume": null,
    "ma50": 183.505,
    "ma200": 164.977,
    "trend": "bullish",
    "volatility_10d": null,
    "sentiment_score": null,
    "buzz": null,
    "pe_ratio": null,
    "peg_ratio": null,
    "dividend_yield": null,
    "timestamp": "2025-11-03T23:37:31.231812",
    "reason": "heuristic fallback",
    "explain_factors": {
      "expectedReturnPct_norm": 0.0,
      "confidence_weight": 0.5354,
      "model_quality_norm": 0.4621,
      "technical": 0.8,
      "sentiment_factor": 1.0,
      "fundamentals": 1.0,
      "health_factor": 1.0
    }
  },
  {
    "ticker": "PLTR",
    "rank": 18,
    "currentPrice": 0.0,
    "predictedPrice": 0.0,
    "expectedReturnPct": null,
    "confidence": 0.64,
    "score": 50.0,
    "rankingScore": 0.48639,
    "horizon": "1y",
    "sector": null,
    "marketCap": 491501902783,
    "marketCapBucket": "mega",
    "volume": null,
    "ma50": 175.759,
    "ma200": 133.179,
    "trend": "bullish",
    "volatility_10d": null,
    "sentiment_score": null,
    "buzz": null,
    "pe_ratio": null,
    "peg_ratio": null,
    "dividend_yield": null,
    "timestamp": "2025-11-03T23:37:31.234831",
    "reason": "heuristic fallback",
    "explain_factors": {
      "expectedReturnPct_norm": 0.0,
      "confidence_weight": 0.5354,
      "model_quality_norm": 0.4621,
      "technical": 0.8,
      "sentiment_factor": 1.0,
      "fundamentals": 1.0,
      "health_factor": 1.0
    }
  },
  {
    "ticker": "AMD",
    "rank": 19,
    "currentPrice": 0.0,
    "predictedPrice": 0.0,
    "expectedReturnPct": null,
    "confidence": 0.64,
    "score": 50.0,
    "rankingScore": 0.48639,
    "horizon": "1y",
    "sector": null,
    "marketCap": 421371363849,
    "marketCapBucket": "mega",
    "volume": null,
    "ma50": 193.107,
    "ma200": 140.12,
    "trend": "bullish",
    "volatility_10d": null,
    "sentiment_score": null,
    "buzz": null,
    "pe_ratio": null,
    "peg_ratio": null,
    "dividend_yield": null,
    "timestamp": "2025-11-03T23:37:31.243341",
    "reason": "heuristic fallback",
    "explain_factors": {
      "expectedReturnPct_norm": 0.0,
      "confidence_weight": 0.5354,
      "model_quality_norm": 0.4621,
      "technical": 0.8,
      "sentiment_factor": 1.0,
      "fundamentals": 1.0,
      "health_factor": 1.0
    }
  },
  {
    "ticker": "ASML",
    "rank": 20,
    "currentPrice": 0.0,
    "predictedPrice": 0.0,
    "expectedReturnPct": null,
    "confidence": 0.64,
    "score": 50.0,
    "rankingScore": 0.48639,
    "horizon": "1y",
    "sector": null,
    "marketCap": 413707132818.1639,
    "marketCapBucket": "mega",
    "volume": null,
    "ma50": 931.148,
    "ma200": 778.315,
    "trend": "bullish",
    "volatility_10d": null,
    "sentiment_score": null,
    "buzz": null,
    "pe_ratio": null,
    "peg_ratio": null,
    "dividend_yield": null,
    "timestamp": "2025-11-03T23:37:31.250687",
    "reason": "heuristic fallback",
    "explain_factors": {
      "expectedReturnPct_norm": 0.0,
      "confidence_weight": 0.5354,
      "model_quality_norm": 0.4621,
      "technical": 0.8,
      "sentiment_factor": 1.0,
      "fundamentals": 1.0,
      "health_factor": 1.0
    }
  },
  {
    "ticker": "ABBV",
    "rank": 21,
    "currentPrice": 0.0,
    "predictedPrice": 0.0,
    "expectedReturnPct": null,
    "confidence": 0.64,
    "score": 50.0,
    "rankingScore": 0.48639,
    "horizon": "1y",
    "sector": null,
    "marketCap": 374439687306,
    "marketCapBucket": "mega",
    "volume": null,
    "ma50": 222.398,
    "ma200": 199.74,
    "trend": "bullish",
    "volatility_10d": null,
    "sentiment_score": null,
    "buzz": null,
    "pe_ratio": null,
    "peg_ratio": null,
    "dividend_yield": null,
    "timestamp": "2025-11-03T23:37:31.253540",
    "reason": "heuristic fallback",
    "explain_factors": {
      "expectedReturnPct_norm": 0.0,
      "confidence_weight": 0.5354,
      "model_quality_norm": 0.4621,
      "technical": 0.8,
      "sentiment_factor": 1.0,
      "fundamentals": 1.0,
      "health_factor": 1.0
    }
  },
  {
    "ticker": "BABA",
    "rank": 22,
    "currentPrice": 0.0,
    "predictedPrice": 0.0,
    "expectedReturnPct": null,
    "confidence": 0.64,
    "score": 50.0,
    "rankingScore": 0.48639,
    "horizon": "1y",
    "sector": null,
    "marketCap": 374676278738,
    "marketCapBucket": "mega",
    "volume": null,
    "ma50": 162.042,
    "ma200": 129.919,
    "trend": "bullish",
    "volatility_10d": null,
    "sentiment_score": null,
    "buzz": null,
    "pe_ratio": null,
    "peg_ratio": null,
    "dividend_yield": null,
    "timestamp": "2025-11-03T23:37:31.262150",
    "reason": "heuristic fallback",
    "explain_factors": {
      "expectedReturnPct_norm": 0.0,
      "confidence_weight": 0.5354,
      "model_quality_norm": 0.4621,
      "technical": 0.8,
      "sentiment_factor": 1.0,
      "fundamentals": 1.0,
      "health_factor": 1.0
    }
  },
  {
    "ticker": "BAC",
    "rank": 23,
    "currentPrice": 0.0,
    "predictedPrice": 0.0,
    "expectedReturnPct": null,
    "confidence": 0.64,
    "score": 50.0,
    "rankingScore": 0.48639,
    "horizon": "1y",
    "sector": null,
    "marketCap": 391121661658,
    "marketCapBucket": "mega",
    "volume": null,
    "ma50": 51.101,
    "ma200": 45.895,
    "trend": "bullish",
    "volatility_10d": null,
    "sentiment_score": null,
    "buzz": null,
    "pe_ratio": null,
    "peg_ratio": null,
    "dividend_yield": null,
    "timestamp": "2025-11-03T23:37:31.267170",
    "reason": "heuristic fallback",
    "explain_factors": {
      "expectedReturnPct_norm": 0.0,
      "confidence_weight": 0.5354,
      "model_quality_norm": 0.4621,
      "technical": 0.8,
      "sentiment_factor": 1.0,
      "fundamentals": 1.0,
      "health_factor": 1.0
    }
  },
  {
    "ticker": "HD",
    "rank": 24,
    "currentPrice": 0.0,
    "predictedPrice": 0.0,
    "expectedReturnPct": null,
    "confidence": 0.64,
    "score": 50.0,
    "rankingScore": 0.48639,
    "horizon": "1y",
    "sector": null,
    "marketCap": 376604537892,
    "marketCapBucket": "mega",
    "volume": null,
    "ma50": 399.938,
    "ma200": 381.602,
    "trend": "bullish",
    "volatility_10d": null,
    "sentiment_score": null,
    "buzz": null,
    "pe_ratio": null,
    "peg_ratio": null,
    "dividend_yield": null,
    "timestamp": "2025-11-03T23:37:31.267170",
    "reason": "heuristic fallback",
    "explain_factors": {
      "expectedReturnPct_norm": 0.0,
      "confidence_weight": 0.5354,
      "model_quality_norm": 0.4621,
      "technical": 0.8,
      "sentiment_factor": 1.0,
      "fundamentals": 1.0,
      "health_factor": 1.0
    }
  },
  {
    "ticker": "GE",
    "rank": 25,
    "currentPrice": 0.0,
    "predictedPrice": 0.0,
    "expectedReturnPct": null,
    "confidence": 0.64,
    "score": 50.0,
    "rankingScore": 0.48639,
    "horizon": "1y",
    "sector": null,
    "marketCap": 325536669213,
    "marketCapBucket": "mega",
    "volume": null,
    "ma50": 294.18,
    "ma200": 242.18,
    "trend": "bullish",
    "volatility_10d": null,
    "sentiment_score": null,
    "buzz": null,
    "pe_ratio": null,
    "peg_ratio": null,
    "dividend_yield": null,
    "timestamp": "2025-11-03T23:37:31.291510",
    "reason": "heuristic fallback",
    "explain_factors": {
      "expectedReturnPct_norm": 0.0,
      "confidence_weight": 0.5354,
      "model_quality_norm": 0.4621,
      "technical": 0.8,
      "sentiment_factor": 1.0,
      "fundamentals": 1.0,
      "health_factor": 1.0
    }
  },
  {
    "ticker": "CVX",
    "rank": 26,
    "currentPrice": 0.0,
    "predictedPrice": 0.0,
    "expectedReturnPct": null,
    "confidence": 0.64,
    "score": 50.0,
    "rankingScore": 0.48639,
    "horizon": "1y",
    "sector": null,
    "marketCap": 312584187519,
    "marketCapBucket": "mega",
    "volume": null,
    "ma50": 155.931,
    "ma200": 151.058,
    "trend": "bullish",
    "volatility_10d": null,
    "sentiment_score": null,
    "buzz": null,
    "pe_ratio": null,
    "peg_ratio": null,
    "dividend_yield": null,
    "timestamp": "2025-11-03T23:37:31.299537",
    "reason": "heuristic fallback",
    "explain_factors": {
      "expectedReturnPct_norm": 0.0,
      "confidence_weight": 0.5354,
      "model_quality_norm": 0.4621,
      "technical": 0.8,
      "sentiment_factor": 1.0,
      "fundamentals": 1.0,
      "health_factor": 1.0
    }
  },
  {
    "ticker": "IBM",
    "rank": 27,
    "currentPrice": 0.0,
    "predictedPrice": 0.0,
    "expectedReturnPct": null,
    "confidence": 0.64,
    "score": 50.0,
    "rankingScore": 0.48639,
    "horizon": "1y",
    "sector": null,
    "marketCap": 284841859324,
    "marketCapBucket": "mega",
    "volume": null,
    "ma50": 274.331,
    "ma200": 260.928,
    "trend": "bullish",
    "volatility_10d": null,
    "sentiment_score": null,
    "buzz": null,
    "pe_ratio": null,
    "peg_ratio": null,
    "dividend_yield": null,
    "timestamp": "2025-11-03T23:37:31.307342",
    "reason": "heuristic fallback",
    "explain_factors": {
      "expectedReturnPct_norm": 0.0,
      "confidence_weight": 0.5354,
      "model_quality_norm": 0.4621,
      "technical": 0.8,
      "sentiment_factor": 1.0,
      "fundamentals": 1.0,
      "health_factor": 1.0
    }
  },
  {
    "ticker": "CSCO",
    "rank": 28,
    "currentPrice": 0.0,
    "predictedPrice": 0.0,
    "expectedReturnPct": null,
    "confidence": 0.64,
    "score": 50.0,
    "rankingScore": 0.48639,
    "horizon": "1y",
    "sector": null,
    "marketCap": 293386969401,
    "marketCapBucket": "mega",
    "volume": null,
    "ma50": 68.93,
    "ma200": 64.799,
    "trend": "bullish",
    "volatility_10d": null,
    "sentiment_score": null,
    "buzz": null,
    "pe_ratio": null,
    "peg_ratio": null,
    "dividend_yield": null,
    "timestamp": "2025-11-03T23:37:31.307342",
    "reason": "heuristic fallback",
    "explain_factors": {
      "expectedReturnPct_norm": 0.0,
      "confidence_weight": 0.5354,
      "model_quality_norm": 0.4621,
      "technical": 0.8,
      "sentiment_factor": 1.0,
      "fundamentals": 1.0,
      "health_factor": 1.0
    }
  },
  {
    "ticker": "WFC",
    "rank": 29,
    "currentPrice": 0.0,
    "predictedPrice": 0.0,
    "expectedReturnPct": null,
    "confidence": 0.64,
    "score": 50.0,
    "rankingScore": 0.48639,
    "horizon": "1y",
    "sector": null,
    "marketCap": 274042080517,
    "marketCapBucket": "mega",
    "volume": null,
    "ma50": 82.865,
    "ma200": 77.243,
    "trend": "bullish",
    "volatility_10d": null,
    "sentiment_score": null,
    "buzz": null,
    "pe_ratio": null,
    "peg_ratio": null,
    "dividend_yield": null,
    "timestamp": "2025-11-03T23:37:31.323103",
    "reason": "heuristic fallback",
    "explain_factors": {
      "expectedReturnPct_norm": 0.0,
      "confidence_weight": 0.5354,
      "model_quality_norm": 0.4621,
      "technical": 0.8,
      "sentiment_factor": 1.0,
      "fundamentals": 1.0,
      "health_factor": 1.0
    }
  },
  {
    "ticker": "TM",
    "rank": 30,
    "currentPrice": 0.0,
    "predictedPrice": 0.0,
    "expectedReturnPct": null,
    "confidence": 0.64,
    "score": 50.0,
    "rankingScore": 0.48639,
    "horizon": "1y",
    "sector": null,
    "marketCap": 265349046390.18915,
    "marketCapBucket": "mega",
    "volume": null,
    "ma50": 198.434,
    "ma200": 186.708,
    "trend": "bullish",
    "volatility_10d": null,
    "sentiment_score": null,
    "buzz": null,
    "pe_ratio": null,
    "peg_ratio": null,
    "dividend_yield": null,
    "timestamp": "2025-11-03T23:37:31.323103",
    "reason": "heuristic fallback",
    "explain_factors": {
      "expectedReturnPct_norm": 0.0,
      "confidence_weight": 0.5354,
      "model_quality_norm": 0.4621,
      "technical": 0.8,
      "sentiment_factor": 1.0,
      "fundamentals": 1.0,
      "health_factor": 1.0
    }
  },
  {
    "ticker": "MS",
    "rank": 31,
    "currentPrice": 0.0,
    "predictedPrice": 0.0,
    "expectedReturnPct": null,
    "confidence": 0.64,
    "score": 50.0,
    "rankingScore": 0.48639,
    "horizon": "1y",
    "sector": null,
    "marketCap": 260367150000,
    "marketCapBucket": "mega",
    "volume": null,
    "ma50": 156.966,
    "ma200": 136.77,
    "trend": "bullish",
    "volatility_10d": null,
    "sentiment_score": null,
    "buzz": null,
    "pe_ratio": null,
    "peg_ratio": null,
    "dividend_yield": null,
    "timestamp": "2025-11-03T23:37:31.323103",
    "reason": "heuristic fallback",
    "explain_factors": {
      "expectedReturnPct_norm": 0.0,
      "confidence_weight": 0.5354,
      "model_quality_norm": 0.4621,
      "technical": 0.8,
      "sentiment_factor": 1.0,
      "fundamentals": 1.0,
      "health_factor": 1.0
    }
  },
  {
    "ticker": "AZN",
    "rank": 32,
    "currentPrice": 0.0,
    "predictedPrice": 0.0,
    "expectedReturnPct": null,
    "confidence": 0.64,
    "score": 50.0,
    "rankingScore": 0.48639,
    "horizon": "1y",
    "sector": null,
    "marketCap": 252039264029.38632,
    "marketCapBucket": "mega",
    "volume": null,
    "ma50": 81.167,
    "ma200": 74.403,
    "trend": "bullish",
    "volatility_10d": null,
    "sentiment_score": null,
    "buzz": null,
    "pe_ratio": null,
    "peg_ratio": null,
    "dividend_yield": null,
    "timestamp": "2025-11-03T23:37:31.323103",
    "reason": "heuristic fallback",
    "explain_factors": {
      "expectedReturnPct_norm": 0.0,
      "confidence_weight": 0.5354,
      "model_quality_norm": 0.4621,
      "technical": 0.8,
      "sentiment_factor": 1.0,
      "fundamentals": 1.0,
      "health_factor": 1.0
    }
  },
  {
    "ticker": "NVS",
    "rank": 33,
    "currentPrice": 0.0,
    "predictedPrice": 0.0,
    "expectedReturnPct": null,
    "confidence": 0.64,
    "score": 50.0,
    "rankingScore": 0.48639,
    "horizon": "1y",
    "sector": null,
    "marketCap": 236436136441.1746,
    "marketCapBucket": "mega",
    "volume": null,
    "ma50": 127.307,
    "ma200": 116.516,
    "trend": "bullish",
    "volatility_10d": null,
    "sentiment_score": null,
    "buzz": null,
    "pe_ratio": null,
    "peg_ratio": null,
    "dividend_yield": null,
    "timestamp": "2025-11-03T23:37:31.338871",
    "reason": "heuristic fallback",
    "explain_factors": {
      "expectedReturnPct_norm": 0.0,
      "confidence_weight": 0.5354,
      "model_quality_norm": 0.4621,
      "technical": 0.8,
      "sentiment_factor": 1.0,
      "fundamentals": 1.0,
      "health_factor": 1.0
    }
  },
  {
    "ticker": "GS",
    "rank": 34,
    "currentPrice": 0.0,
    "predictedPrice": 0.0,
    "expectedReturnPct": null,
    "confidence": 0.64,
    "score": 50.0,
    "rankingScore": 0.48639,
    "horizon": "1y",
    "sector": null,
    "marketCap": 246433393314,
    "marketCapBucket": "mega",
    "volume": null,
    "ma50": 774.572,
    "ma200": 661.357,
    "trend": "bullish",
    "volatility_10d": null,
    "sentiment_score": null,
    "buzz": null,
    "pe_ratio": null,
    "peg_ratio": null,
    "dividend_yield": null,
    "timestamp": "2025-11-03T23:37:31.345247",
    "reason": "heuristic fallback",
    "explain_factors": {
      "expectedReturnPct_norm": 0.0,
      "confidence_weight": 0.5354,
      "model_quality_norm": 0.4621,
      "technical": 0.8,
      "sentiment_factor": 1.0,
      "fundamentals": 1.0,
      "health_factor": 1.0
    }
  },
  {
    "ticker": "AXP",
    "rank": 35,
    "currentPrice": 0.0,
    "predictedPrice": 0.0,
    "expectedReturnPct": null,
    "confidence": 0.64,
    "score": 50.0,
    "rankingScore": 0.48639,
    "horizon": "1y",
    "sector": null,
    "marketCap": 249102534758,
    "marketCapBucket": "mega",
    "volume": null,
    "ma50": 336.209,
    "ma200": 303.602,
    "trend": "bullish",
    "volatility_10d": null,
    "sentiment_score": null,
    "buzz": null,
    "pe_ratio": null,
    "peg_ratio": null,
    "dividend_yield": null,
    "timestamp": "2025-11-03T23:37:31.347253",
    "reason": "heuristic fallback",
    "explain_factors": {
      "expectedReturnPct_norm": 0.0,
      "confidence_weight": 0.5354,
      "model_quality_norm": 0.4621,
      "technical": 0.8,
      "sentiment_factor": 1.0,
      "fundamentals": 1.0,
      "health_factor": 1.0
    }
  },
  {
    "ticker": "MU",
    "rank": 36,
    "currentPrice": 0.0,
    "predictedPrice": 0.0,
    "expectedReturnPct": null,
    "confidence": 0.64,
    "score": 50.0,
    "rankingScore": 0.48639,
    "horizon": "1y",
    "sector": null,
    "marketCap": 263442778415,
    "marketCapBucket": "mega",
    "volume": null,
    "ma50": 172.143,
    "ma200": 118.148,
    "trend": "bullish",
    "volatility_10d": null,
    "sentiment_score": null,
    "buzz": null,
    "pe_ratio": null,
    "peg_ratio": null,
    "dividend_yield": null,
    "timestamp": "2025-11-03T23:37:31.354512",
    "reason": "heuristic fallback",
    "explain_factors": {
      "expectedReturnPct_norm": 0.0,
      "confidence_weight": 0.5354,
      "model_quality_norm": 0.4621,
      "technical": 0.8,
      "sentiment_factor": 1.0,
      "fundamentals": 1.0,
      "health_factor": 1.0
    }
  },
  {
    "ticker": "CAT",
    "rank": 37,
    "currentPrice": 0.0,
    "predictedPrice": 0.0,
    "expectedReturnPct": null,
    "confidence": 0.64,
    "score": 50.0,
    "rankingScore": 0.48639,
    "horizon": "1y",
    "sector": null,
    "marketCap": 267309388675,
    "marketCapBucket": "mega",
    "volume": null,
    "ma50": 481.278,
    "ma200": 391.338,
    "trend": "bullish",
    "volatility_10d": null,
    "sentiment_score": null,
    "buzz": null,
    "pe_ratio": null,
    "peg_ratio": null,
    "dividend_yield": null,
    "timestamp": "2025-11-03T23:37:31.360762",
    "reason": "heuristic fallback",
    "explain_factors": {
      "expectedReturnPct_norm": 0.0,
      "confidence_weight": 0.5354,
      "model_quality_norm": 0.4621,
      "technical": 0.8,
      "sentiment_factor": 1.0,
      "fundamentals": 1.0,
      "health_factor": 1.0
    }
  },
  {
    "ticker": "PANW",
    "rank": 38,
    "currentPrice": 0.0,
    "predictedPrice": 0.0,
    "expectedReturnPct": null,
    "confidence": 0.64,
    "score": 50.0,
    "rankingScore": 0.48639,
    "horizon": "1y",
    "sector": null,
    "marketCap": 148390414642,
    "marketCapBucket": "large",
    "volume": null,
    "ma50": 205.085,
    "ma200": 191.106,
    "trend": "bullish",
    "volatility_10d": null,
    "sentiment_score": null,
    "buzz": null,
    "pe_ratio": null,
    "peg_ratio": null,
    "dividend_yield": null,
    "timestamp": "2025-11-03T23:37:31.656506",
    "reason": "heuristic fallback",
    "explain_factors": {
      "expectedReturnPct_norm": 0.0,
      "confidence_weight": 0.5354,
      "model_quality_norm": 0.4621,
      "technical": 0.8,
      "sentiment_factor": 1.0,
      "fundamentals": 1.0,
      "health_factor": 1.0
    }
  },
  {
    "ticker": "ETN",
    "rank": 39,
    "currentPrice": 0.0,
    "predictedPrice": 0.0,
    "expectedReturnPct": null,
    "confidence": 0.64,
    "score": 50.0,
    "rankingScore": 0.48639,
    "horizon": "1y",
    "sector": null,
    "marketCap": 150491701000,
    "marketCapBucket": "large",
    "volume": null,
    "ma50": 368.074,
    "ma200": 333.321,
    "trend": "bullish",
    "volatility_10d": null,
    "sentiment_score": null,
    "buzz": null,
    "pe_ratio": null,
    "peg_ratio": null,
    "dividend_yield": null,
    "timestamp": "2025-11-03T23:37:31.660522",
    "reason": "heuristic fallback",
    "explain_factors": {
      "expectedReturnPct_norm": 0.0,
      "confidence_weight": 0.5354,
      "model_quality_norm": 0.4621,
      "technical": 0.8,
      "sentiment_factor": 1.0,
      "fundamentals": 1.0,
      "health_factor": 1.0
    }
  },
  {
    "ticker": "SAN",
    "rank": 40,
    "currentPrice": 0.0,
    "predictedPrice": 0.0,
    "expectedReturnPct": null,
    "confidence": 0.64,
    "score": 50.0,
    "rankingScore": 0.48639,
    "horizon": "1y",
    "sector": null,
    "marketCap": 150591262121.2522,
    "marketCapBucket": "large",
    "volume": null,
    "ma50": 9.955,
    "ma200": 8.006,
    "trend": "bullish",
    "volatility_10d": null,
    "sentiment_score": null,
    "buzz": null,
    "pe_ratio": null,
    "peg_ratio": null,
    "dividend_yield": null,
    "timestamp": "2025-11-03T23:37:31.670130",
    "reason": "heuristic fallback",
    "explain_factors": {
      "expectedReturnPct_norm": 0.0,
      "confidence_weight": 0.5354,
      "model_quality_norm": 0.4621,
      "technical": 0.8,
      "sentiment_factor": 1.0,
      "fundamentals": 1.0,
      "health_factor": 1.0
    }
  },
  {
    "ticker": "COF",
    "rank": 41,
    "currentPrice": 0.0,
    "predictedPrice": 0.0,
    "expectedReturnPct": null,
    "confidence": 0.64,
    "score": 50.0,
    "rankingScore": 0.48639,
    "horizon": "1y",
    "sector": null,
    "marketCap": 140934690000,
    "marketCapBucket": "large",
    "volume": null,
    "ma50": 219.756,
    "ma200": 201.278,
    "trend": "bullish",
    "volatility_10d": null,
    "sentiment_score": null,
    "buzz": null,
    "pe_ratio": null,
    "peg_ratio": null,
    "dividend_yield": null,
    "timestamp": "2025-11-03T23:37:31.673198",
    "reason": "heuristic fallback",
    "explain_factors": {
      "expectedReturnPct_norm": 0.0,
      "confidence_weight": 0.5354,
      "model_quality_norm": 0.4621,
      "technical": 0.8,
      "sentiment_factor": 1.0,
      "fundamentals": 1.0,
      "health_factor": 1.0
    }
  },
  {
    "ticker": "BHP",
    "rank": 42,
    "currentPrice": 0.0,
    "predictedPrice": 0.0,
    "expectedReturnPct": null,
    "confidence": 0.64,
    "score": 50.0,
    "rankingScore": 0.48639,
    "horizon": "1y",
    "sector": null,
    "marketCap": 143837034485.48914,
    "marketCapBucket": "large",
    "volume": null,
    "ma50": 55.28,
    "ma200": 51.143,
    "trend": "bullish",
    "volatility_10d": null,
    "sentiment_score": null,
    "buzz": null,
    "pe_ratio": null,
    "peg_ratio": null,
    "dividend_yield": null,
    "timestamp": "2025-11-03T23:37:31.681152",
    "reason": "heuristic fallback",
    "explain_factors": {
      "expectedReturnPct_norm": 0.0,
      "confidence_weight": 0.5354,
      "model_quality_norm": 0.4621,
      "technical": 0.8,
      "sentiment_factor": 1.0,
      "fundamentals": 1.0,
      "health_factor": 1.0
    }
  },
  {
    "ticker": "PFE",
    "rank": 43,
    "currentPrice": 0.0,
    "predictedPrice": 0.0,
    "expectedReturnPct": null,
    "confidence": 0.64,
    "score": 50.0,
    "rankingScore": 0.48639,
    "horizon": "1y",
    "sector": null,
    "marketCap": 140205675330,
    "marketCapBucket": "large",
    "volume": null,
    "ma50": 24.772,
    "ma200": 24.661,
    "trend": "bullish",
    "volatility_10d": null,
    "sentiment_score": null,
    "buzz": null,
    "pe_ratio": null,
    "peg_ratio": null,
    "dividend_yield": null,
    "timestamp": "2025-11-03T23:37:31.686173",
    "reason": "heuristic fallback",
    "explain_factors": {
      "expectedReturnPct_norm": 0.0,
      "confidence_weight": 0.5354,
      "model_quality_norm": 0.4621,
      "technical": 0.8,
      "sentiment_factor": 1.0,
      "fundamentals": 1.0,
      "health_factor": 1.0
    }
  },
  {
    "ticker": "TD",
    "rank": 44,
    "currentPrice": 0.0,
    "predictedPrice": 0.0,
    "expectedReturnPct": null,
    "confidence": 0.64,
    "score": 50.0,
    "rankingScore": 0.48639,
    "horizon": "1y",
    "sector": null,
    "marketCap": 140871839139.24164,
    "marketCapBucket": "large",
    "volume": null,
    "ma50": 78.597,
    "ma200": 68.666,
    "trend": "bullish",
    "volatility_10d": null,
    "sentiment_score": null,
    "buzz": null,
    "pe_ratio": null,
    "peg_ratio": null,
    "dividend_yield": null,
    "timestamp": "2025-11-03T23:37:31.691579",
    "reason": "heuristic fallback",
    "explain_factors": {
      "expectedReturnPct_norm": 0.0,
      "confidence_weight": 0.5354,
      "model_quality_norm": 0.4621,
      "technical": 0.8,
      "sentiment_factor": 1.0,
      "fundamentals": 1.0,
      "health_factor": 1.0
    }
  },
  {
    "ticker": "LOW",
    "rank": 45,
    "currentPrice": 0.0,
    "predictedPrice": 0.0,
    "expectedReturnPct": null,
    "confidence": 0.64,
    "score": 50.0,
    "rankingScore": 0.48639,
    "horizon": "1y",
    "sector": null,
    "marketCap": 132152780614,
    "marketCapBucket": "large",
    "volume": null,
    "ma50": 252.522,
    "ma200": 238.056,
    "trend": "bullish",
    "volatility_10d": null,
    "sentiment_score": null,
    "buzz": null,
    "pe_ratio": null,
    "peg_ratio": null,
    "dividend_yield": null,
    "timestamp": "2025-11-03T23:37:31.700798",
    "reason": "heuristic fallback",
    "explain_factors": {
      "expectedReturnPct_norm": 0.0,
      "confidence_weight": 0.5354,
      "model_quality_norm": 0.4621,
      "technical": 0.8,
      "sentiment_factor": 1.0,
      "fundamentals": 1.0,
      "health_factor": 1.0
    }
  },
  {
    "ticker": "TTE",
    "rank": 46,
    "currentPrice": 0.0,
    "predictedPrice": 0.0,
    "expectedReturnPct": null,
    "confidence": 0.64,
    "score": 50.0,
    "rankingScore": 0.48639,
    "horizon": "1y",
    "sector": null,
    "marketCap": 133942350458.50089,
    "marketCapBucket": "large",
    "volume": null,
    "ma50": 61.162,
    "ma200": 60.646,
    "trend": "bullish",
    "volatility_10d": null,
    "sentiment_score": null,
    "buzz": null,
    "pe_ratio": null,
    "peg_ratio": null,
    "dividend_yield": null,
    "timestamp": "2025-11-03T23:37:31.702805",
    "reason": "heuristic fallback",
    "explain_factors": {
      "expectedReturnPct_norm": 0.0,
      "confidence_weight": 0.5354,
      "model_quality_norm": 0.4621,
      "technical": 0.8,
      "sentiment_factor": 1.0,
      "fundamentals": 1.0,
      "health_factor": 1.0
    }
  },
  {
    "ticker": "SPOT",
    "rank": 47,
    "currentPrice": 0.0,
    "predictedPrice": 0.0,
    "expectedReturnPct": null,
    "confidence": 0.64,
    "score": 50.0,
    "rankingScore": 0.48639,
    "horizon": "1y",
    "sector": null,
    "marketCap": 132539398082,
    "marketCapBucket": "large",
    "volume": null,
    "ma50": 690.88,
    "ma200": 647.683,
    "trend": "bullish",
    "volatility_10d": null,
    "sentiment_score": null,
    "buzz": null,
    "pe_ratio": null,
    "peg_ratio": null,
    "dividend_yield": null,
    "timestamp": "2025-11-03T23:37:31.710317",
    "reason": "heuristic fallback",
    "explain_factors": {
      "expectedReturnPct_norm": 0.0,
      "confidence_weight": 0.5354,
      "model_quality_norm": 0.4621,
      "technical": 0.8,
      "sentiment_factor": 1.0,
      "fundamentals": 1.0,
      "health_factor": 1.0
    }
  },
  {
    "ticker": "CRWD",
    "rank": 48,
    "currentPrice": 0.0,
    "predictedPrice": 0.0,
    "expectedReturnPct": null,
    "confidence": 0.64,
    "score": 50.0,
    "rankingScore": 0.48639,
    "horizon": "1y",
    "sector": null,
    "marketCap": 138507160869,
    "marketCapBucket": "large",
    "volume": null,
    "ma50": 478.018,
    "ma200": 437.706,
    "trend": "bullish",
    "volatility_10d": null,
    "sentiment_score": null,
    "buzz": null,
    "pe_ratio": null,
    "peg_ratio": null,
    "dividend_yield": null,
    "timestamp": "2025-11-03T23:37:31.714563",
    "reason": "heuristic fallback",
    "explain_factors": {
      "expectedReturnPct_norm": 0.0,
      "confidence_weight": 0.5354,
      "model_quality_norm": 0.4621,
      "technical": 0.8,
      "sentiment_factor": 1.0,
      "fundamentals": 1.0,
      "health_factor": 1.0
    }
  },
  {
    "ticker": "HOOD",
    "rank": 49,
    "currentPrice": 0.0,
    "predictedPrice": 0.0,
    "expectedReturnPct": null,
    "confidence": 0.64,
    "score": 50.0,
    "rankingScore": 0.48639,
    "horizon": "1y",
    "sector": null,
    "marketCap": 130706332678,
    "marketCapBucket": "large",
    "volume": null,
    "ma50": 127.84,
    "ma200": 82.286,
    "trend": "bullish",
    "volatility_10d": null,
    "sentiment_score": null,
    "buzz": null,
    "pe_ratio": null,
    "peg_ratio": null,
    "dividend_yield": null,
    "timestamp": "2025-11-03T23:37:31.741917",
    "reason": "heuristic fallback",
    "explain_factors": {
      "expectedReturnPct_norm": 0.0,
      "confidence_weight": 0.5354,
      "model_quality_norm": 0.4621,
      "technical": 0.8,
      "sentiment_factor": 1.0,
      "fundamentals": 1.0,
      "health_factor": 1.0
    }
  },
  {
    "ticker": "CEG",
    "rank": 50,
    "currentPrice": 0.0,
    "predictedPrice": 0.0,
    "expectedReturnPct": null,
    "confidence": 0.64,
    "score": 50.0,
    "rankingScore": 0.48639,
    "horizon": "1y",
    "sector": null,
    "marketCap": 117998711244,
    "marketCapBucket": "large",
    "volume": null,
    "ma50": 346.991,
    "ma200": 297.076,
    "trend": "bullish",
    "volatility_10d": null,
    "sentiment_score": null,
    "buzz": null,
    "pe_ratio": null,
    "peg_ratio": null,
    "dividend_yield": null,
    "timestamp": "2025-11-03T23:37:31.745866",
    "reason": "heuristic fallback",
    "explain_factors": {
      "expectedReturnPct_norm": 0.0,
      "confidence_weight": 0.5354,
      "model_quality_norm": 0.4621,
      "technical": 0.8,
      "sentiment_factor": 1.0,
      "fundamentals": 1.0,
      "health_factor": 1.0
    }
  }
]